energnn/__init__.py
energnn/amortizer/__init__.py
energnn/amortizer/simple_amortizer.py
energnn/amortizer/utils.py
energnn/feature_store/__init__.py
energnn/feature_store/config_info.py
energnn/feature_store/feature_store_client.py
energnn/gnn/__init__.py
energnn/gnn/encoder.py
energnn/gnn/gnn.py
energnn/gnn/utils.py
energnn/gnn/coupler/__init__.py
energnn/gnn/coupler/coupler.py
energnn/gnn/coupler/solving_method.py
energnn/gnn/coupler/coupling_function/__init__.py
energnn/gnn/coupler/coupling_function/coupling_function.py
energnn/gnn/coupler/coupling_function/local_message_function.py
energnn/gnn/coupler/coupling_function/remote_message_function.py
energnn/gnn/coupler/coupling_function/self_message_function.py
energnn/gnn/decoder/__init__.py
energnn/gnn/decoder/equivariant_decoder.py
energnn/gnn/decoder/invariant_decoder.py
energnn/graph/__init__.py
energnn/graph/edge.py
energnn/graph/graph.py
energnn/graph/shape.py
energnn/graph/utils.py
energnn/graph/jax/__init__.py
energnn/graph/jax/edge.py
energnn/graph/jax/graph.py
energnn/graph/jax/shape.py
energnn/graph/jax/utils.py
energnn/normalizer/__init__.py
energnn/normalizer/postprocessor.py
energnn/normalizer/preprocessor.py
energnn/normalizer/utils.py
energnn/normalizer/normalization_function/__init__.py
energnn/normalizer/normalization_function/cdf_pw_linear_function.py
energnn/normalizer/normalization_function/center_reduce_function.py
energnn/normalizer/normalization_function/identity_function.py
energnn/normalizer/normalization_function/normalization_function.py
energnn/problem/__init__.py
energnn/problem/batch.py
energnn/problem/dataset.py
energnn/problem/loader.py
energnn/problem/metadata.py
energnn/problem/problem.py
energnn/storage/__init__.py
energnn/storage/dummy.py
energnn/storage/storage.py
energnn/tracker/__init__.py
energnn/tracker/dummy.py
energnn/tracker/neptune.py
energnn/tracker/neptune_scale.py
energnn/tracker/tracker.py
energnn-0.1.0.dist-info/METADATA
energnn-0.1.0.dist-info/WHEEL
energnn-0.1.0.dist-info/licenses/LICENSE
energnn-0.1.0.dist-info/RECORD
